hata/__init__.py
hata/__main__.py
hata/vampytest_config.py
hata/discord/__init__.py
hata/discord/color.py
hata/discord/core.py
hata/discord/field_parsers.py
hata/discord/field_putters.py
hata/discord/field_validators.py
hata/discord/object_binding.py
hata/discord/payload_building.py
hata/discord/preconverters.py
hata/discord/precreate_helpers.py
hata/discord/utils.py
hata/discord/activity/__init__.py
hata/discord/activity/activity/__init__.py
hata/discord/activity/activity/activity.py
hata/discord/activity/activity/constants.py
hata/discord/activity/activity/fields.py
hata/discord/activity/activity/preinstanced.py
hata/discord/activity/activity_assets/__init__.py
hata/discord/activity/activity_assets/assets.py
hata/discord/activity/activity_assets/fields.py
hata/discord/activity/activity_field_base/__init__.py
hata/discord/activity/activity_field_base/base.py
hata/discord/activity/activity_metadata/__init__.py
hata/discord/activity/activity_metadata/base.py
hata/discord/activity/activity_metadata/custom.py
hata/discord/activity/activity_metadata/fields.py
hata/discord/activity/activity_metadata/flags.py
hata/discord/activity/activity_metadata/hanging.py
hata/discord/activity/activity_metadata/preinstanced.py
hata/discord/activity/activity_metadata/rich.py
hata/discord/activity/activity_party/__init__.py
hata/discord/activity/activity_party/fields.py
hata/discord/activity/activity_party/party.py
hata/discord/activity/activity_secrets/__init__.py
hata/discord/activity/activity_secrets/fields.py
hata/discord/activity/activity_secrets/secrets.py
hata/discord/activity/activity_timestamps/__init__.py
hata/discord/activity/activity_timestamps/fields.py
hata/discord/activity/activity_timestamps/timestamps.py
hata/discord/allowed_mentions/__init__.py
hata/discord/allowed_mentions/constants.py
hata/discord/allowed_mentions/helpers.py
hata/discord/allowed_mentions/proxy.py
hata/discord/allowed_mentions/utils.py
hata/discord/ansi_format/__init__.py
hata-1.3.90.dist-info/LICENSE
hata-1.3.90.dist-info/METADATA
hata-1.3.90.dist-info/WHEEL
hata-1.3.90.dist-info/entry_points.txt
hata-1.3.90.dist-info/top_level.txt
hata-1.3.90.dist-info/RECORD
