Metadata-Version: 2.1
Name: hata
Version: 1.3.90
Summary: A powerful asynchronous library for creating Discord bots in Python.
Home-page: https://github.com/HuyaneMatsu/hata
Author: HuyaneMatsu
Author-email: re.ism.tm@gmail.com
License: DBAD
Platform: UNKNOWN
Classifier: Development Status :: 5 - Production/Stable
Classifier: Intended Audience :: Developers
Classifier: Operating System :: POSIX :: Linux
Classifier: Programming Language :: Python
Classifier: Programming Language :: Python :: 3.6
Classifier: Programming Language :: Python :: 3.7
Classifier: Programming Language :: Python :: 3.8
Classifier: Programming Language :: Python :: 3.9
Classifier: Programming Language :: Python :: 3.10
Classifier: Programming Language :: Python :: 3.11
Classifier: Programming Language :: Python :: Implementation :: CPython
Classifier: Programming Language :: Python :: Implementation :: PyPy
Classifier: Topic :: Communications :: Chat
Classifier: Topic :: Software Development :: Libraries
Classifier: Topic :: Software Development :: Libraries :: Python Modules
Requires-Python: >=3.6,<3.12
Requires-Dist: scarletio (>=1.0.91)
Requires-Dist: chardet (>=2.0)
Provides-Extra: all
Requires-Dist: PyNaCl (>=1.3.0) ; extra == 'all'
Requires-Dist: cchardet (>=2.0) ; extra == 'all'
Requires-Dist: inotify-simple (>=1.3.5) ; extra == 'all'
Requires-Dist: python-dateutil (>=2.0) ; extra == 'all'
Requires-Dist: snakeviz ; extra == 'all'
Requires-Dist: yappi ; extra == 'all'
Provides-Extra: autoreload
Requires-Dist: inotify-simple (>=1.3.5) ; extra == 'autoreload'
Provides-Extra: cpythonspeedups
Requires-Dist: cchardet (>=2.0) ; extra == 'cpythonspeedups'
Provides-Extra: profiling
Requires-Dist: snakeviz ; extra == 'profiling'
Requires-Dist: yappi ; extra == 'profiling'
Provides-Extra: relativedelta
Requires-Dist: python-dateutil (>=2.0) ; extra == 'relativedelta'
Provides-Extra: voice
Requires-Dist: PyNaCl (>=1.3.0) ; extra == 'voice'
Requires-Dist: libnacl ; extra == 'voice'
